example_package_a155/__init__.py
example_package_a155/example.py
example_package_a155-0.0.8.dist-info/METADATA
example_package_a155-0.0.8.dist-info/WHEEL
example_package_a155-0.0.8.dist-info/top_level.txt
example_package_a155-0.0.8.dist-info/RECORD
