Metadata-Version: 2.1
Name: example-package-a155
Version: 0.0.8
Summary: A small example package
Author-email: Example Author <author@example.com>
Classifier: Programming Language :: Python :: 3
Classifier: License :: OSI Approved :: MIT License
Classifier: Operating System :: OS Independent
Requires-Dist: web3
Requires-Dist: ipfshttpclient ==0.8.0a2
Requires-Dist: requests
